{
  "concursoCurriculoId": 1664,
  "concursoCurriculoPlanoPagamentoId": 4992,
  "concursoFilialId": 2011,
  "diaVencimento": 10,
  "formaPagamentoId": 1,
  "pessoa": {
    "cpf": "142.025.113-95",
    "email": "rodrigo.lopes.costa.novo.138@emailteste.com",
    "endereco": {
      "bairro": "Jardim das Flores",
      "cep": "37520-413",
      "cidadeId": 10677,
      "logradouro": "Alameda Campinas",
      "numero": "5",
      "ufId": 26
    },
    "generoId": 3,
    "nascimento": "2003-09-05",
    "nome": "Rodrigo Lopes Costa",
    "racaId": 10,
    "telefone": "(89) 97182-4436"
  },
  "termoIds": [
    3,
    5
  ]
}