{
  "concursoCurriculoId": 1664,
  "concursoCurriculoPlanoPagamentoId": 4992,
  "concursoFilialId": 2011,
  "diaVencimento": 10,
  "formaPagamentoId": 1,
  "pessoa": {
    "cpf": "882.439.652-62",
    "email": "carlos.nascimento.mendes.novo.32@emailteste.com",
    "endereco": {
      "bairro": "Ipanema",
      "cep": "53260-457",
      "cidadeId": 10677,
      "logradouro": "Rua Vergueiro",
      "numero": "2120",
      "ufId": 26
    },
    "generoId": 3,
    "nascimento": "2003-04-24",
    "nome": "Carlos Nascimento Mendes",
    "racaId": 10,
    "telefone": "(53) 98662-6766"
  },
  "termoIds": [
    3,
    5
  ]
}